<annotation>
	<folder>shuffle</folder>
	<filename>596.jpg</filename>
	<path>C:\CV_DeepLearning\LOGOdetection\img_logo\resized\shuffle\596.jpg</path>
	<source>
		<database>Unknown</database>
	</source>
	<size>
		<width>500</width>
		<height>500</height>
		<depth>3</depth>
	</size>
	<segmented>0</segmented>
	<object>
		<name>starbucks</name>
		<pose>Unspecified</pose>
		<truncated>0</truncated>
		<difficult>0</difficult>
		<bndbox>
			<xmin>330</xmin>
			<ymin>51</ymin>
			<xmax>388</xmax>
			<ymax>118</ymax>
		</bndbox>
	</object>
	<object>
		<name>starbucks</name>
		<pose>Unspecified</pose>
		<truncated>0</truncated>
		<difficult>0</difficult>
		<bndbox>
			<xmin>60</xmin>
			<ymin>226</ymin>
			<xmax>150</xmax>
			<ymax>318</ymax>
		</bndbox>
	</object>
</annotation>
